odoo/addons/maintenance_equipment_category_kanban/README.rst
odoo/addons/maintenance_equipment_category_kanban/__init__.py
odoo/addons/maintenance_equipment_category_kanban/__manifest__.py
odoo/addons/maintenance_equipment_category_kanban/i18n/es.po
odoo/addons/maintenance_equipment_category_kanban/i18n/it.po
odoo/addons/maintenance_equipment_category_kanban/i18n/maintenance_equipment_category_kanban.pot
odoo/addons/maintenance_equipment_category_kanban/models/__init__.py
odoo/addons/maintenance_equipment_category_kanban/models/maintenance_equipment_category.py
odoo/addons/maintenance_equipment_category_kanban/readme/CONTRIBUTORS.rst
odoo/addons/maintenance_equipment_category_kanban/readme/DESCRIPTION.rst
odoo/addons/maintenance_equipment_category_kanban/static/description/icon.png
odoo/addons/maintenance_equipment_category_kanban/static/description/index.html
odoo/addons/maintenance_equipment_category_kanban/views/maintenance_equipment_category_views.xml
odoo/addons/maintenance_equipment_category_kanban/views/maintenance_equipment_views.xml
odoo13_addon_maintenance_equipment_category_kanban-13.0.1.1.0.dist-info/METADATA
odoo13_addon_maintenance_equipment_category_kanban-13.0.1.1.0.dist-info/WHEEL
odoo13_addon_maintenance_equipment_category_kanban-13.0.1.1.0.dist-info/top_level.txt
odoo13_addon_maintenance_equipment_category_kanban-13.0.1.1.0.dist-info/RECORD
